NRUtil/NRObjStoreUtil.py
NRUtil/__about__.py
NRUtil/__init__.py
NRUtil/constants.py
nr_objstore_util-0.11.0.dist-info/METADATA
nr_objstore_util-0.11.0.dist-info/WHEEL
nr_objstore_util-0.11.0.dist-info/licenses/LICENSE
nr_objstore_util-0.11.0.dist-info/RECORD
