Metadata-Version: 2.3
Name: nr_objstore_util
Version: 0.11.0
Summary: Utility to bundle commonly used object store operations into an easy to use module
Project-URL: Homepage, https://github.com/bcgov/nr-objectstore-util
Project-URL: Bug Tracker, https://github.com/bcgov/nr-objectstore-util/issues
Author-email: Kevin Netherton <kevin.netherton@gov.bc.ca>
License-File: LICENSE
Classifier: License :: OSI Approved :: MIT License
Classifier: Operating System :: OS Independent
Classifier: Programming Language :: Python :: 3
Requires-Python: >=3.8
Requires-Dist: boto3==1.35.1
Requires-Dist: minio==7.2.8
Requires-Dist: python-dotenv==1.0.1
